scripter/__init__.py
scripter/dialogue.py
scripter/scene.py
scripter/script.py
playscripter-0.1.dist-info/LICENSE
playscripter-0.1.dist-info/METADATA
playscripter-0.1.dist-info/WHEEL
playscripter-0.1.dist-info/top_level.txt
playscripter-0.1.dist-info/RECORD
