Metadata-Version: 2.1
Name: playscripter
Version: 0.1
Summary: A Python alternative to making playscripts.
Home-page: https://github.com/NCPlayz/Scripter
Author: NCPlayz <Nadir Chowdhury>
Author-email: chowdhurynadir0@outlook.com
License: MIT
Platform: UNKNOWN
Classifier: Operating System :: OS Independent
Classifier: Programming Language :: Python :: 3
Classifier: Intended Audience :: Education
Classifier: License :: OSI Approved :: MIT License
Classifier: Topic :: Utilities
Classifier: Natural Language :: English
Classifier: Development Status :: 3 - Alpha
Classifier: Topic :: Software Development :: Libraries :: Python Modules
Requires-Python: >=3
Requires-Dist: python-docx (==0.8.7)
